dtit/pyLiteMath/__init__.py
dtit/pyLiteMath/tests/hello.py
dtit/pyLiteMath/tests/test_fft.py
dtit/pyLiteMath/tests/test_litemath.py
dtit/pyLiteMath/tests/test_log.py
dtit.pyLiteMath-0.0.2.dist-info/LICENSE
dtit.pyLiteMath-0.0.2.dist-info/METADATA
dtit.pyLiteMath-0.0.2.dist-info/WHEEL
dtit.pyLiteMath-0.0.2.dist-info/top_level.txt
dtit.pyLiteMath-0.0.2.dist-info/RECORD
